README.rst
setup.py
src/benchsuite/__init__.py
src/benchsuite.scheduler.egg-info/PKG-INFO
src/benchsuite.scheduler.egg-info/SOURCES.txt
src/benchsuite.scheduler.egg-info/dependency_links.txt
src/benchsuite.scheduler.egg-info/entry_points.txt
src/benchsuite.scheduler.egg-info/namespace_packages.txt
src/benchsuite.scheduler.egg-info/requires.txt
src/benchsuite.scheduler.egg-info/top_level.txt
src/benchsuite/scheduler/__init__.py
src/benchsuite/scheduler/bsscheduler.py
src/benchsuite/scheduler/cli.py
src/benchsuite/scheduler/config.py
src/benchsuite/scheduler/dockermanager.py
src/benchsuite/scheduler/logger.py
src/benchsuite/scheduler/schedules.py
src/benchsuite/scheduler/synchronizer.py
src/benchsuite/scheduler/jobs/__init__.py
src/benchsuite/scheduler/jobs/benchmarking.py
src/benchsuite/scheduler/jobs/meta.py